MANIFEST.in
setup.py
docs/HISTORY.txt
src/dolmen/__init__.py
src/dolmen.app.container.egg-info/PKG-INFO
src/dolmen.app.container.egg-info/SOURCES.txt
src/dolmen.app.container.egg-info/dependency_links.txt
src/dolmen.app.container.egg-info/namespace_packages.txt
src/dolmen.app.container.egg-info/not-zip-safe
src/dolmen.app.container.egg-info/requires.txt
src/dolmen.app.container.egg-info/top_level.txt
src/dolmen/app/__init__.py
src/dolmen/app/container/README.txt
src/dolmen/app/container/__init__.py
src/dolmen/app/container/addtofolder.py
src/dolmen/app/container/configure.zcml
src/dolmen/app/container/ftesting.zcml
src/dolmen/app/container/listing.py
src/dolmen/app/container/namechoosers.py
src/dolmen/app/container/tests.py
src/dolmen/app/container/templates/addmenu.pt
src/dolmen/app/container/templates/folderlisting.pt